{
  "imageUrl": "/img/tiles.png",

  "frames": [
    {
      "name": "bang-1",
      "rect": [256, 128, 16, 16]
    },
    {
      "name": "bang-2",
      "rect": [272, 128, 16, 16]
    },
    {
      "name": "bang-3",
      "rect": [288, 128, 16, 16]
    },
    {
      "name": "run-top",
      "rect": [320, 99, 8, 8]
    },
    {
      "name": "run-left",
      "rect": [328, 99, 8, 8]
    },
    {
      "name": "run-bottom",
      "rect": [336, 99, 8, 8]
    },
    {
      "name": "run-right",
      "rect": [344, 99, 8, 8]
    }
  ],

  "animations": [
    {
      "name": "bang",
      "frameLen": 0.2,
      "frames": ["bang-1", "bang-2", "bang-3"]
    }
  ]
}
